Connection_Tool/Connection.py
Connection_Tool/__init__.py
wbs_connectdb-0.1.3.dist-info/LICENSE
wbs_connectdb-0.1.3.dist-info/METADATA
wbs_connectdb-0.1.3.dist-info/WHEEL
wbs_connectdb-0.1.3.dist-info/top_level.txt
wbs_connectdb-0.1.3.dist-info/RECORD
