Metadata-Version: 2.1
Name: wbs-connectdb
Version: 0.1.3
Summary: UNKNOWN
Home-page: https://xxxxxxxxx
Author: WangBensen
Author-email: OTLXmao@126.com
License: Apache License
Platform: UNKNOWN
Classifier: Environment :: Web Environment
Classifier: Intended Audience :: Developers
Classifier: Operating System :: OS Independent
Classifier: Topic :: Text Processing :: Indexing
Classifier: Topic :: Utilities
Classifier: Topic :: Internet
Classifier: Topic :: Software Development :: Libraries :: Python Modules
Classifier: Programming Language :: Python
Classifier: Programming Language :: Python :: 3.9
License-File: LICENSE
Requires-Dist: psycopg2-binary (<=2.9.3)
Requires-Dist: pymysql (<=1.0.2)
